whatamithinking/pycona/__init__.py
whatamithinking/pycona/_appindicator.py
whatamithinking/pycona/_base.py
whatamithinking/pycona/_darwin.py
whatamithinking/pycona/_dummy.py
whatamithinking/pycona/_gtk.py
whatamithinking/pycona/_image.py
whatamithinking/pycona/_info.py
whatamithinking/pycona/_win32.py
whatamithinking/pycona/_xorg.py
whatamithinking/pycona/_util/__init__.py
whatamithinking/pycona/_util/gtk.py
whatamithinking/pycona/_util/notify_dbus.py
whatamithinking/pycona/_util/win32.py
whatamithinking_pycona-1.0.0.dist-info/licenses/COPYING
whatamithinking_pycona-1.0.0.dist-info/licenses/COPYING.LGPL
whatamithinking_pycona-1.0.0.dist-info/METADATA
whatamithinking_pycona-1.0.0.dist-info/WHEEL
whatamithinking_pycona-1.0.0.dist-info/top_level.txt
whatamithinking_pycona-1.0.0.dist-info/zip-safe
whatamithinking_pycona-1.0.0.dist-info/RECORD
