Metadata-Version: 2.4
Name: whatamithinking-pycona
Version: 1.0.0
Summary: Provides systray integration
Home-page: https://github.com/whatamithinking/pycona
Author: Moses Palmér
Author-email: moses.palmer@gmail.com
Maintainer: Connor Maynes
Maintainer-email: connormaynes@gmail.com
License: LGPLv3
Keywords: system tray icon,systray icon
Classifier: Development Status :: 4 - Beta
Classifier: Intended Audience :: Developers
Classifier: License :: OSI Approved :: GNU Lesser General Public License v3 (LGPLv3)
Classifier: Operating System :: MacOS :: MacOS X
Classifier: Operating System :: Microsoft :: Windows :: Windows NT/2000
Classifier: Operating System :: POSIX
Classifier: Programming Language :: Python
Classifier: Programming Language :: Python :: 3.7
License-File: COPYING
License-File: COPYING.LGPL
Requires-Dist: six
Requires-Dist: pyobjc-framework-Quartz>=7.0; sys_platform == "darwin"
Requires-Dist: Pillow; sys_platform == "darwin"
Requires-Dist: python-xlib>=0.17; sys_platform == "linux"
Requires-Dist: Pillow; sys_platform == "arch"
Dynamic: author
Dynamic: author-email
Dynamic: classifier
Dynamic: description
Dynamic: description-content-type
Dynamic: home-page
Dynamic: keywords
Dynamic: license
Dynamic: license-file
Dynamic: maintainer
Dynamic: maintainer-email
Dynamic: provides-extra
Dynamic: requires-dist
Dynamic: summary
